omxplayer/__init__.py
omxplayer/__version__.py
omxplayer/bus_finder.py
omxplayer/dbus_connection.py
omxplayer/keys.py
omxplayer/player.py
omxplayer_wrapper-0.3.3.dist-info/LICENSE.txt
omxplayer_wrapper-0.3.3.dist-info/METADATA
omxplayer_wrapper-0.3.3.dist-info/WHEEL
omxplayer_wrapper-0.3.3.dist-info/top_level.txt
omxplayer_wrapper-0.3.3.dist-info/RECORD
