Metadata-Version: 2.1
Name: omxplayer-wrapper
Version: 0.3.3
Summary: A library for controlling omxplayer on the Raspberry Pi
Home-page: https://github.com/willprice/python-omxplayer-wrapper
Author: Will Price
Author-email: will.price94+dev@gmail.com
License: LGPLv3+
Keywords: omxplayer pi raspberry raspberrypi raspberry_pi library video media
Platform: UNKNOWN
Classifier: Development Status :: 4 - Beta
Classifier: Intended Audience :: Developers
Classifier: License :: OSI Approved :: GNU Lesser General Public License v3 or later (LGPLv3+)
Classifier: Topic :: Multimedia :: Video
Classifier: Programming Language :: Python :: 2
Classifier: Programming Language :: Python :: 2.7
Classifier: Programming Language :: Python :: 3
Classifier: Programming Language :: Python :: 3.4
Classifier: Programming Language :: Python :: 3.5
Classifier: Programming Language :: Python :: 3.6
Classifier: Programming Language :: Python :: 3.7
Requires-Dist: dbus-python
Requires-Dist: evento
Requires-Dist: decorator
Requires-Dist: pathlib2
Provides-Extra: docs
Requires-Dist: Sphinx ; extra == 'docs'
Requires-Dist: alabaster ; extra == 'docs'
Requires-Dist: pygments ; extra == 'docs'
Provides-Extra: test
Requires-Dist: mock ; extra == 'test'
Requires-Dist: pytest ; extra == 'test'
Requires-Dist: pytest-cov ; extra == 'test'
Requires-Dist: nose ; extra == 'test'
Requires-Dist: parameterized ; extra == 'test'
